onemetric/__init__.py
onemetric/const.py
onemetric/cv.py
onemetric/general.py
onemetric/cv/__init__.py
onemetric/cv/loaders/__init__.py
onemetric/cv/loaders/base.py
onemetric/cv/loaders/coco/__init__.py
onemetric/cv/loaders/coco/core.py
onemetric/cv/loaders/coco/dataclasses.py
onemetric/cv/loaders/yolo/__init__.py
onemetric/cv/loaders/yolo/core.py
onemetric/cv/loaders/yolo/dataclasses.py
onemetric/cv/object_detection/__init__.py
onemetric/cv/object_detection/average_precision.py
onemetric/cv/object_detection/confusion_matrix.py
onemetric/cv/object_detection/mean_average_precision.py
onemetric/cv/utils/__init__.py
onemetric/cv/utils/iou.py
onemetric/cv/utils/validators.py
onemetric/utils/__init__.py
onemetric/utils/general.py
tests/cv/__init__.py
tests/cv/object_detection/__init__.py
tests/cv/object_detection/test_average_precision.py
tests/cv/object_detection/test_confusion_matrix.py
tests/cv/utils/__init__.py
tests/cv/utils/test_iou.py
onemetric-0.1.2.dist-info/LICENSE.md
onemetric-0.1.2.dist-info/METADATA
onemetric-0.1.2.dist-info/WHEEL
onemetric-0.1.2.dist-info/top_level.txt
onemetric-0.1.2.dist-info/RECORD
